CONTRIBUTING.md
MANIFEST.in
README.rst
setup.cfg
setup.py
docs/HISTORY.txt
docs/LICENSE.GPL
docs/LICENSE.txt
eea/__init__.py
eea.faceted.vocabularies.egg-info/PKG-INFO
eea.faceted.vocabularies.egg-info/SOURCES.txt
eea.faceted.vocabularies.egg-info/dependency_links.txt
eea.faceted.vocabularies.egg-info/entry_points.txt
eea.faceted.vocabularies.egg-info/namespace_packages.txt
eea.faceted.vocabularies.egg-info/not-zip-safe
eea.faceted.vocabularies.egg-info/requires.txt
eea.faceted.vocabularies.egg-info/top_level.txt
eea/faceted/__init__.py
eea/faceted/vocabularies/README.txt
eea/faceted/vocabularies/__init__.py
eea/faceted/vocabularies/autocomplete.py
eea/faceted/vocabularies/catalog.py
eea/faceted/vocabularies/configure.zcml
eea/faceted/vocabularies/faceted.py
eea/faceted/vocabularies/portal.py
eea/faceted/vocabularies/position.py
eea/faceted/vocabularies/section.py
eea/faceted/vocabularies/simple.py
eea/faceted/vocabularies/tests.py
eea/faceted/vocabularies/types.py
eea/faceted/vocabularies/utils.py
eea/faceted/vocabularies/version.txt
eea/faceted/vocabularies/locales/eea.pot
eea/faceted/vocabularies/locales/update.sh
eea/faceted/vocabularies/locales/bg/LC_MESSAGES/eea.po
eea/faceted/vocabularies/locales/cs/LC_MESSAGES/eea.po
eea/faceted/vocabularies/locales/da/LC_MESSAGES/eea.po
eea/faceted/vocabularies/locales/de/LC_MESSAGES/eea.po
eea/faceted/vocabularies/locales/el/LC_MESSAGES/eea.po
eea/faceted/vocabularies/locales/en/LC_MESSAGES/eea.po
eea/faceted/vocabularies/locales/es/LC_MESSAGES/eea.po
eea/faceted/vocabularies/locales/et/LC_MESSAGES/eea.po
eea/faceted/vocabularies/locales/fi/LC_MESSAGES/eea.po
eea/faceted/vocabularies/locales/fr/LC_MESSAGES/eea.po
eea/faceted/vocabularies/locales/hu/LC_MESSAGES/eea.po
eea/faceted/vocabularies/locales/is/LC_MESSAGES/eea.po
eea/faceted/vocabularies/locales/it/LC_MESSAGES/eea.po
eea/faceted/vocabularies/locales/kl/LC_MESSAGES/eea.po
eea/faceted/vocabularies/locales/lt/LC_MESSAGES/eea.po
eea/faceted/vocabularies/locales/lv/LC_MESSAGES/eea.po
eea/faceted/vocabularies/locales/mt/LC_MESSAGES/eea.po
eea/faceted/vocabularies/locales/nl/LC_MESSAGES/eea.po
eea/faceted/vocabularies/locales/no/LC_MESSAGES/eea.po
eea/faceted/vocabularies/locales/pl/LC_MESSAGES/eea.po
eea/faceted/vocabularies/locales/pt/LC_MESSAGES/eea.po
eea/faceted/vocabularies/locales/pt_BR/LC_MESSAGES/eea.po
